fileguard/__init__.py
fileguard/fileguard.py
fileguard/guardjournal.py
fileguard/largefileguard.py
pyfileguard-0.0.4.dist-info/LICENSE
pyfileguard-0.0.4.dist-info/METADATA
pyfileguard-0.0.4.dist-info/WHEEL
pyfileguard-0.0.4.dist-info/top_level.txt
pyfileguard-0.0.4.dist-info/RECORD
