Metadata-Version: 2.1
Name: pyfileguard
Version: 0.0.4
Summary: File Guard and Large File Guard for preserving file content
Home-page: https://github.com/kr-g/pyfileguard
Author: k.r. goger
Author-email: k.r.goger+pyfileguard@gmail.com
License: MIT
Keywords: utility test testing file handling bim guard before-image copy-on-write
Platform: UNKNOWN
Classifier: Development Status :: 3 - Alpha
Classifier: Operating System :: POSIX :: Linux
Classifier: Intended Audience :: Developers
Classifier: Topic :: Utilities
Classifier: Programming Language :: Python :: 3
Classifier: License :: OSI Approved :: MIT License
Requires-Python: >=3.6
